sdk/__init__.py
sdk/client.py
sdk/core/__init__.py
sdk/core/configs/__init__.py
sdk/core/configs/variables.py
sdk/core/models/__init__.py
sdk/core/models/movie.py
sdk/core/models/quote.py
sdk/core/utils/__init__.py
sdk/core/utils/errors.py
sdk/core/utils/helpers.py
emmanuelsdk-0.0.4.dist-info/METADATA
emmanuelsdk-0.0.4.dist-info/WHEEL
emmanuelsdk-0.0.4.dist-info/top_level.txt
emmanuelsdk-0.0.4.dist-info/RECORD
